.gitignore
.travis.yml
MANIFEST.in
README.md
README.rst
pytest.ini
requirements.txt
setup.py
pyenv_mirror_download/__init__.py
pyenv_mirror_download/download.py
pyenv_mirror_download/locate_scripts.py
pyenv_mirror_download/main.py
pyenv_mirror_download/metadata.py
pyenv_mirror_download/parse_script.py
pyenv_mirror_download.egg-info/PKG-INFO
pyenv_mirror_download.egg-info/SOURCES.txt
pyenv_mirror_download.egg-info/dependency_links.txt
pyenv_mirror_download.egg-info/entry_points.txt
pyenv_mirror_download.egg-info/requires.txt
pyenv_mirror_download.egg-info/top_level.txt
scripts/install-from-source.sh
scripts/install-from-yum.sh
scripts/pip-install-pkgs-of-requirements.sh
scripts/push-to-pypi.sh
scripts/update-readme-rst.sh
tests/__init__.py
tests/env.py
tests/test_misc.py
tests/__pycache__/__init__.cpython-35.pyc
tests/__pycache__/env.cpython-35.pyc
tests/__pycache__/test_main.cpython-35-PYTEST.pyc
tests/__pycache__/test_misc.cpython-35-PYTEST.pyc
tests/test_pyenv_root/plugins/python-build/share/python-build/2.7
tests/test_pyenv_root/plugins/python-build/share/python-build/2.7.11
tests/test_pyenv_root/plugins/python-build/share/python-build/anaconda3-2.5.0