Metadata-Version: 1.1
Name: pyenv-mirror-download
Version: 0.1.0
Summary:  Download Source Packages For yyuu.github.com/pythons. 
Home-page: UNKNOWN
Author: huntzhan
Author-email: programmer.zhx@gmail.com
License: UNKNOWN
Platform: UNKNOWN
Classifier: Development Status :: 4 - Beta
Classifier: Intended Audience :: Developers
Classifier: Topic :: Software Development :: Testing
Classifier: Programming Language :: Python
Classifier: Operating System :: OS Independent
